tokenize_all.py
tokenize_all-1.0.17.dist-info/LICENSE
tokenize_all-1.0.17.dist-info/METADATA
tokenize_all-1.0.17.dist-info/WHEEL
tokenize_all-1.0.17.dist-info/top_level.txt
tokenize_all-1.0.17.dist-info/RECORD
