Metadata-Version: 2.1
Name: tokenize-all
Version: 1.0.17
Summary: Tokenize code snippets.
Author: Nicholas Iapalucci
License: MIT License
Project-URL: Homepage, https://github.com/NicholasIapalucci/Tokenize-All
Classifier: License :: OSI Approved :: MIT License
Classifier: Programming Language :: Python :: 3
Classifier: Operating System :: OS Independent
Requires-Python: >=3.9
License-File: LICENSE
